preallocate_cuda_memory/__init__.py
preallocate_cuda_memory/__main__.py
preallocate_cuda_memory/utils.py
preallocate_cuda_memory-1.0.0.dist-info/LICENSE
preallocate_cuda_memory-1.0.0.dist-info/METADATA
preallocate_cuda_memory-1.0.0.dist-info/WHEEL
preallocate_cuda_memory-1.0.0.dist-info/top_level.txt
preallocate_cuda_memory-1.0.0.dist-info/RECORD
