Metadata-Version: 2.1
Name: preallocate_cuda_memory
Version: 1.0.0
Summary: preallocate CUDA memory for pytorch
Home-page: https://github.com/guyi2000/preallocate-cuda-memory
Author: Yi Gu
Author-email: guyi2000@yeah.net
Classifier: Programming Language :: Python :: 3
Classifier: License :: OSI Approved :: MIT License
Classifier: Operating System :: OS Independent
Requires-Python: >=3.10
License-File: LICENSE
